sbe2/schema/__init__.py
sbe2/schema/builtin.py
sbe2/schema/common.py
sbe2/schema/composite.py
sbe2/schema/data.py
sbe2/schema/enum.py
sbe2/schema/field.py
sbe2/schema/group.py
sbe2/schema/message.py
sbe2/schema/message_schema.py
sbe2/schema/messages.py
sbe2/schema/primitive_type.py
sbe2/schema/ref.py
sbe2/schema/set.py
sbe2/schema/type.py
sbe2/schema/types.py
sbe2/xmlparser/__init__.py
sbe2/xmlparser/attributes.py
sbe2/xmlparser/ctx.py
sbe2/xmlparser/errors.py
sbe2/xmlparser/types.py
sbe2-0.1.1.dist-info/METADATA
sbe2-0.1.1.dist-info/WHEEL
sbe2-0.1.1.dist-info/licenses/LICENSE
sbe2-0.1.1.dist-info/RECORD
