Metadata-Version: 2.4
Name: sbe2
Version: 0.1.1
Summary: Simple Binary Encoding (SBE) 2.0 library for Python with linter
Project-URL: Homepage, https://github.com/szymonwieloch/py-simple-binary-encoding
Author: Szymon Wieloch
License: MIT
License-File: LICENSE
Classifier: License :: OSI Approved :: MIT License
Classifier: Operating System :: OS Independent
Classifier: Programming Language :: Python :: 3
Classifier: Programming Language :: Python :: 3.12
Requires-Python: >=3.12
Requires-Dist: lxml
Provides-Extra: test
Requires-Dist: pytest; extra == 'test'
Requires-Dist: pytest-cov; extra == 'test'
